vrchatapi/__init__.py
vrchatapi/api_client.py
vrchatapi/configuration.py
vrchatapi/exceptions.py
vrchatapi/rest.py
vrchatapi/api/__init__.py
vrchatapi/api/authentication_api.py
vrchatapi/api/avatars_api.py
vrchatapi/api/calendar_api.py
vrchatapi/api/economy_api.py
vrchatapi/api/favorites_api.py
vrchatapi/api/files_api.py
vrchatapi/api/friends_api.py
vrchatapi/api/groups_api.py
vrchatapi/api/instances_api.py
vrchatapi/api/inventory_api.py
vrchatapi/api/invite_api.py
vrchatapi/api/jams_api.py
vrchatapi/api/miscellaneous_api.py
vrchatapi/api/notifications_api.py
vrchatapi/api/playermoderation_api.py
vrchatapi/api/prints_api.py
vrchatapi/api/props_api.py
vrchatapi/api/users_api.py
vrchatapi/api/worlds_api.py
vrchatapi/models/__init__.py
vrchatapi/models/account_deletion_log.py
vrchatapi/models/add_favorite_request.py
vrchatapi/models/add_group_gallery_image_request.py
vrchatapi/models/admin_asset_bundle.py
vrchatapi/models/admin_unity_package.py
vrchatapi/models/age_verification_status.py
vrchatapi/models/api_config.py
vrchatapi/models/api_config_access_logs_urls.py
vrchatapi/models/api_config_announcement.py
vrchatapi/models/api_config_avatar_perf_limiter.py
vrchatapi/models/api_config_constants.py
vrchatapi/models/api_config_constants_groups.py
vrchatapi/models/api_config_constants_instance.py
vrchatapi/models/api_config_constants_instancepopulationbrackets.py
vrchatapi/models/api_config_constants_instancepopulationbracketscrowded.py
vrchatapi/models/api_config_constants_instancepopulationbracketsfew.py
vrchatapi/models/api_config_constants_instancepopulationbracketsmany.py
vrchatapi/models/api_config_constants_language.py
vrchatapi/models/api_config_download_url_list.py
vrchatapi/models/api_config_events.py
vrchatapi/models/api_config_min_supported_client_build_number.py
vrchatapi/models/api_config_offline_analysis.py
vrchatapi/models/api_config_report_categories.py
vrchatapi/models/api_config_report_options.py
vrchatapi/models/api_config_report_options_avatar.py
vrchatapi-1.20.5.dist-info/licenses/LICENSE
vrchatapi-1.20.5.dist-info/METADATA
vrchatapi-1.20.5.dist-info/WHEEL
vrchatapi-1.20.5.dist-info/top_level.txt
vrchatapi-1.20.5.dist-info/RECORD
