Metadata-Version: 2.4
Name: vrchatapi
Version: 1.20.5
Summary: VRChat API Library for Python
Home-page: 
Author: Unofficial VRChat API Documentation Project
Author-email: vrchatapi.lpv0t@aries.fyi
License: MIT
Keywords: vrchat,vrchatapi,vrc
License-File: LICENSE
Requires-Dist: urllib3>=1.25.3
Requires-Dist: six>=1.10
Requires-Dist: python-dateutil
Dynamic: author
Dynamic: author-email
Dynamic: description
Dynamic: description-content-type
Dynamic: keywords
Dynamic: license
Dynamic: license-file
Dynamic: requires-dist
Dynamic: summary
